[
  { "id": 1, "name": "Lomo Saltado", "calories": 650, "macros": { "p": 35, "c": 75, "g": 22 }, "tags": ["criollo", "restaurante", "carne", "almuerzo", "cena"] },
  { "id": 2, "name": "Ceviche Mixto", "calories": 320, "macros": { "p": 45, "c": 30, "g": 4 }, "tags": ["criollo", "pescado", "saludable", "marino", "almuerzo"] },
  { "id": 3, "name": "Ají de Gallina", "calories": 580, "macros": { "p": 30, "c": 55, "g": 26 }, "tags": ["criollo", "pollo", "casero", "almuerzo", "cena"] },
  { "id": 4, "name": "Pollo a la Brasa (1/4 con papas y ensalada)", "calories": 950, "macros": { "p": 55, "c": 80, "g": 45 }, "tags": ["fastfood", "pollo", "común", "restaurante", "cena"] },
  { "id": 5, "name": "Chaufa de Pollo", "calories": 720, "macros": { "p": 32, "c": 95, "g": 24 }, "tags": ["chifa", "arroz", "restaurante", "almuerzo", "cena"] },
  { "id": 6, "name": "Tallarines Verdes con Bistec", "calories": 810, "macros": { "p": 42, "c": 85, "g": 35 }, "tags": ["casero", "pasta", "carne", "almuerzo"] },
  { "id": 7, "name": "Arroz con Pollo", "calories": 610, "macros": { "p": 35, "c": 75, "g": 18 }, "tags": ["casero", "arroz", "pollo", "almuerzo"] },
  { "id": 8, "name": "Causa Rellena de Pollo", "calories": 410, "macros": { "p": 18, "c": 50, "g": 15 }, "tags": ["entrada", "papa", "pollo", "snack", "piqueo"] },
  { "id": 9, "name": "Papa Rellena", "calories": 380, "macros": { "p": 12, "c": 45, "g": 16 }, "tags": ["entrada", "frito", "carne", "snack"] },
  { "id": 10, "name": "Seco de Res con Frijoles", "calories": 790, "macros": { "p": 48, "c": 88, "g": 25 }, "tags": ["criollo", "carne", "guiso", "almuerzo"] },
  { "id": 11, "name": "Carapulcra con Sopa Seca", "calories": 850, "macros": { "p": 34, "c": 110, "g": 30 }, "tags": ["criollo", "cerdo", "pasta", "almuerzo"] },
  { "id": 12, "name": "Tacu Tacu con Sábana de Lomo", "calories": 890, "macros": { "p": 52, "c": 98, "g": 28 }, "tags": ["criollo", "arroz", "frijoles", "carne", "almuerzo"] },
  { "id": 13, "name": "Papa a la Huancaína", "calories": 420, "macros": { "p": 10, "c": 45, "g": 24 }, "tags": ["entrada", "papa", "queso", "crema"] },
  { "id": 14, "name": "Anticuchos (2 palitos con papa y choclo)", "calories": 480, "macros": { "p": 45, "c": 40, "g": 16 }, "tags": ["callejero", "carne", "noche", "almuerzo", "cena"] },
  { "id": 15, "name": "Menu Ejecutivo Estándar (Sopa + Segundo)", "calories": 850, "macros": { "p": 40, "c": 110, "g": 28 }, "tags": ["restaurante", "almuerzo", "diario", "común"] },
  { "id": 16, "name": "Pan con Chicharrón", "calories": 640, "macros": { "p": 28, "c": 55, "g": 34 }, "tags": ["desayuno", "cerdo", "callejero", "snack"] },
  { "id": 17, "name": "Empanada de Carne", "calories": 350, "macros": { "p": 12, "c": 38, "g": 18 }, "tags": ["snack", "piqueo", "panadería"] },
  { "id": 18, "name": "Choclo con Queso fresco serrano", "calories": 280, "macros": { "p": 12, "c": 35, "g": 10 }, "tags": ["snack", "saludable", "queso", "maíz", "merienda"] },
  { "id": 19, "name": "Cancha Serrana (puñado de 30g)", "calories": 120, "macros": { "p": 3, "c": 22, "g": 2 }, "tags": ["snack", "piqueo", "cancha", "merienda"] },
  { "id": 20, "name": "Camote al Horno (100g)", "calories": 110, "macros": { "p": 2, "c": 25, "g": 0 }, "tags": ["snack", "carbohidrato", "saludable", "merienda"] },
  { "id": 21, "name": "Ensalada de Frutas (plato mediano sin yogur)", "calories": 160, "macros": { "p": 3, "c": 38, "g": 0 }, "tags": ["snack", "frutas", "saludable", "desayuno", "merienda"] },
  { "id": 22, "name": "Yogurt Griego con Granola y Chía", "calories": 240, "macros": { "p": 18, "c": 26, "g": 6 }, "tags": ["snack", "desayuno", "lácteo", "proteína", "merienda"] },
  { "id": 23, "name": "Barra de Proteína", "calories": 200, "macros": { "p": 20, "c": 18, "g": 5 }, "tags": ["snack", "fitness", "proteína", "merienda", "entreno"] },
  { "id": 24, "name": "Almendras y Nueces (puñado 30g)", "calories": 170, "macros": { "p": 6, "c": 5, "g": 15 }, "tags": ["snack", "grasas", "saludable", "frutos-secos", "merienda"] },
  { "id": 25, "name": "Huevo Duro (1 unidad mediana)", "calories": 75, "macros": { "p": 6, "c": 0.5, "g": 5 }, "tags": ["snack", "huevo", "proteína", "desayuno", "merienda"] },
  { "id": 26, "name": "Palta Mediana (media porción / 100g)", "calories": 160, "macros": { "p": 2, "c": 8, "g": 15 }, "tags": ["snack", "grasas", "palta", "saludable", "desayuno", "merienda"] },
  { "id": 27, "name": "Chicha Morada tradicional (vaso 250ml)", "calories": 110, "macros": { "p": 0, "c": 28, "g": 0 }, "tags": ["bebida", "chicha", "dulce"] },
  { "id": 28, "name": "Chicha Morada Zero (vaso 250ml sin azúcar)", "calories": 5, "macros": { "p": 0, "c": 1, "g": 0 }, "tags": ["bebida", "chicha", "zero", "saludable"] },
  { "id": 29, "name": "Emoliente con Limón y linaza (vaso 250ml)", "calories": 60, "macros": { "p": 0, "c": 15, "g": 0 }, "tags": ["bebida", "caliente", "emoliente", "saludable"] },
  { "id": 30, "name": "Inka Kola Zero (lata 355ml)", "calories": 0, "macros": { "p": 0, "c": 0, "g": 0 }, "tags": ["bebida", "gaseosa", "zero", "refresco"] },
  { "id": 31, "name": "Inka Kola Regular (lata 355ml)", "calories": 140, "macros": { "p": 0, "c": 35, "g": 0 }, "tags": ["bebida", "gaseosa", "dulce"] },
  { "id": 32, "name": "Jugo de Papaya natural (vaso sin azúcar)", "calories": 80, "macros": { "p": 1, "c": 19, "g": 0 }, "tags": ["bebida", "jugo", "desayuno", "frutas", "saludable"] },
  { "id": 33, "name": "Café Negro con 1 cdta de azúcar", "calories": 20, "macros": { "p": 0, "c": 5, "g": 0 }, "tags": ["bebida", "café", "caliente", "desayuno"] },
  { "id": 34, "name": "Café Negro Solo (sin azúcar)", "calories": 2, "macros": { "p": 0, "c": 0, "g": 0 }, "tags": ["bebida", "café", "zero", "desayuno", "saludable"] },
  { "id": 35, "name": "Té o Manzanilla caliente con miel", "calories": 45, "macros": { "p": 0, "c": 11, "g": 0 }, "tags": ["bebida", "infusión", "caliente", "cena"] },
  { "id": 36, "name": "Limonada Casera (vaso 250ml con azúcar)", "calories": 90, "macros": { "p": 0, "c": 22, "g": 0 }, "tags": ["bebida", "limón", "dulce"] },
  { "id": 37, "name": "Batido de Avena y Plátano con leche descremada", "calories": 320, "macros": { "p": 10, "c": 58, "g": 5 }, "tags": ["bebida", "batido", "desayuno", "merienda", "entreno"] },
  { "id": 38, "name": "Tiradito de Pescado clásico", "calories": 240, "macros": { "p": 38, "c": 15, "g": 3 }, "tags": ["criollo", "pescado", "marino", "saludable", "almuerzo"] },
  { "id": 39, "name": "Arroz con Mariscos", "calories": 780, "macros": { "p": 38, "c": 98, "g": 26 }, "tags": ["criollo", "mariscos", "arroz", "restaurante", "almuerzo"] },
  { "id": 40, "name": "Jalea Mixta Personal", "calories": 890, "macros": { "p": 45, "c": 85, "g": 42 }, "tags": ["criollo", "mariscos", "frito", "restaurante", "almuerzo"] },
  { "id": 41, "name": "Escabeche de Pollo", "calories": 520, "macros": { "p": 32, "c": 48, "g": 22 }, "tags": ["criollo", "pollo", "casero", "almuerzo", "cena"] },
  { "id": 42, "name": "Rocoto Relleno Arequipeño con Papa al Horno", "calories": 550, "macros": { "p": 28, "c": 45, "g": 28 }, "tags": ["criollo", "carne", "queso", "horno", "almuerzo"] },
  { "id": 43, "name": "Chupe de Camarones", "calories": 710, "macros": { "p": 42, "c": 62, "g": 32 }, "tags": ["criollo", "mariscos", "sopa", "lácteo", "almuerzo"] },
  { "id": 44, "name": "Cau Cau de Mondongo", "calories": 490, "macros": { "p": 25, "c": 52, "g": 20 }, "tags": ["criollo", "mondongo", "papa", "guiso", "almuerzo"] },
  { "id": 45, "name": "Chanfainita con Mote y Papa", "calories": 560, "macros": { "p": 26, "c": 72, "g": 18 }, "tags": ["criollo", "bofe", "papa", "callejero", "almuerzo"] },
  { "id": 46, "name": "Mondonguito a la Italiana", "calories": 510, "macros": { "p": 28, "c": 48, "g": 22 }, "tags": ["criollo", "mondongo", "verduras", "almuerzo"] },
  { "id": 47, "name": "Arroz con Pato a la Chiclayana", "calories": 840, "macros": { "p": 45, "c": 92, "g": 32 }, "tags": ["criollo", "pato", "arroz", "restaurante", "almuerzo"] },
  { "id": 48, "name": "Tallarines Rojos con Pollo", "calories": 690, "macros": { "p": 38, "c": 82, "g": 24 }, "tags": ["casero", "pasta", "pollo", "almuerzo", "cena"] },
  { "id": 49, "name": "Sudado de Pescado criollo", "calories": 280, "macros": { "p": 36, "c": 22, "g": 5 }, "tags": ["criollo", "pescado", "caldo", "saludable", "almuerzo"] },
  { "id": 50, "name": "Chicharrón de Pescado (porción regular)", "calories": 620, "macros": { "p": 34, "c": 45, "g": 33 }, "tags": ["criollo", "pescado", "frito", "piqueo", "almuerzo"] },
  { "id": 51, "name": "Pepián de Choclo con Pollo", "calories": 480, "macros": { "p": 28, "c": 54, "g": 16 }, "tags": ["criollo", "maíz", "pollo", "almuerzo"] },
  { "id": 52, "name": "Adobo Arequipeño con pan", "calories": 740, "macros": { "p": 42, "c": 68, "g": 32 }, "tags": ["criollo", "cerdo", "caldo", "desayuno", "almuerzo"] },
  { "id": 53, "name": "Cuy Chactado (media porción con papas)", "calories": 780, "macros": { "p": 54, "c": 48, "g": 42 }, "tags": ["andino", "cuy", "frito", "almuerzo"] },
  { "id": 54, "name": "Tamal Criollo de Pollo o Cerdo", "calories": 390, "macros": { "p": 10, "c": 46, "g": 18 }, "tags": ["desayuno", "maíz", "piqueo", "domingo"] },
  { "id": 55, "name": "Humita Dulce o Salada", "calories": 260, "macros": { "p": 6, "c": 38, "g": 9 }, "tags": ["snack", "piqueo", "maíz", "desayuno", "merienda"] },
  { "id": 56, "name": "Tequeños con Guacamole (5 unidades)", "calories": 380, "macros": { "p": 12, "c": 30, "g": 24 }, "tags": ["snack", "piqueo", "queso", "palta", "entrada"] },
  { "id": 57, "name": "Salchipapa Clásica Mediana", "calories": 840, "macros": { "p": 18, "c": 82, "g": 48 }, "tags": ["fastfood", "papa", "embutido", "cena", "tarde"] },
  { "id": 58, "name": "Ocopa Arequipeña (entrada estándar)", "calories": 440, "macros": { "p": 11, "c": 46, "g": 25 }, "tags": ["entrada", "papa", "crema", "almuerzo"] },
  { "id": 59, "name": "Pan con Lomo al Jugo", "calories": 480, "macros": { "p": 24, "c": 52, "g": 18 }, "tags": ["desayuno", "carne", "sándwich"] },
  { "id": 60, "name": "Pan con Pollo deshilachado y mayonesa", "calories": 390, "macros": { "p": 22, "c": 42, "g": 15 }, "tags": ["desayuno", "sándwich", "pollo", "snack"] },
  { "id": 61, "name": "Yuca Sancochada (100g)", "calories": 160, "macros": { "p": 1.5, "c": 38, "g": 0 }, "tags": ["snack", "carbohidrato", "saludable", "almuerzo"] },
  { "id": 62, "name": "Plátano Madurito Frito (1 unidad)", "calories": 190, "macros": { "p": 1, "c": 32, "g": 7 }, "tags": ["snack", "dulce", "fritura", "almuerzo"] },
  { "id": 63, "name": "Salpicón de Pollo (ensalada fresca con papa)", "calories": 310, "macros": { "p": 26, "c": 28, "g": 10 }, "tags": ["saludable", "ensalada", "pollo", "almuerzo", "cena"] },
  { "id": 64, "name": "Tamalito Verde Piurano", "calories": 320, "macros": { "p": 8, "c": 42, "g": 14 }, "tags": ["entrada", "maíz", "culantro", "desayuno"] },
  { "id": 65, "name": "Mazamorra Morada (porción clásica)", "calories": 180, "macros": { "p": 1, "c": 44, "g": 0 }, "tags": ["postre", "dulce", "maíz", "tarde"] },
  { "id": 66, "name": "Arroz con Leche peruano", "calories": 260, "macros": { "p": 6, "c": 48, "g": 5 }, "tags": ["postre", "dulce", "lácteo", "tarde"] },
  { "id": 67, "name": "Suspiro a la Limeña (vasito chico)", "calories": 340, "macros": { "p": 6, "c": 58, "g": 10 }, "tags": ["postre", "dulce", "limeño"] },
  { "id": 68, "name": "Picarones con miel de chancaca (2 unidades)", "calories": 290, "macros": { "p": 3, "c": 52, "g": 8 }, "tags": ["postre", "dulce", "frito", "callejero", "noche"] },
  { "id": 69, "name": "Crema Volteada (porción mediana)", "calories": 310, "macros": { "p": 8, "c": 45, "g": 11 }, "tags": ["postre", "dulce", "huevo", "lácteo"] },
  { "id": 70, "name": "Emoliente Caliente Sin Azúcar (vaso)", "calories": 5, "macros": { "p": 0, "c": 1, "g": 0 }, "tags": ["bebida", "caliente", "zero", "saludable"] },
  { "id": 71, "name": "Coca Cola Zero (lata 355ml)", "calories": 0, "macros": { "p": 0, "c": 0, "g": 0 }, "tags": ["bebida", "gaseosa", "zero", "refresco"] },
  { "id": 72, "name": "Coca Cola Regular (lata 355ml)", "calories": 140, "macros": { "p": 0, "c": 35, "g": 0 }, "tags": ["bebida", "gaseosa", "dulce"] },
  { "id": 73, "name": "Jugo de Piña natural (vaso sin azúcar)", "calories": 90, "macros": { "p": 1, "c": 21, "g": 0 }, "tags": ["bebida", "jugo", "desayuno", "saludable"] },
  { "id": 74, "name": "Jugo de Fresa con leche descremada", "calories": 150, "macros": { "p": 8, "c": 24, "g": 2 }, "tags": ["bebida", "jugo", "lácteo", "desayuno", "merienda"] },
  { "id": 75, "name": "Café con Leche descremada (sin azúcar)", "calories": 70, "macros": { "p": 6, "c": 9, "g": 1 }, "tags": ["bebida", "café", "lácteo", "desayuno"] },
  { "id": 76, "name": "Mate de Coca caliente", "calories": 2, "macros": { "p": 0, "c": 0.5, "g": 0 }, "tags": ["bebida", "infusión", "caliente", "saludable"] },
  { "id": 77, "name": "Avena / Quaker con manzana peruana (vaso)", "calories": 160, "macros": { "p": 4, "c": 32, "g": 2 }, "tags": ["bebida", "avena", "caliente", "desayuno"] },
  { "id": 78, "name": "Ponche de Habas caliente (vaso)", "calories": 190, "macros": { "p": 8, "c": 36, "g": 2 }, "tags": ["bebida", "habas", "caliente", "desayuno", "andino"] },
  { "id": 79, "name": "Limonada Zero (vaso con edulcorante)", "calories": 2, "macros": { "p": 0, "c": 0.5, "g": 0 }, "tags": ["bebida", "limón", "zero", "saludable"] },
  { "id": 80, "name": "Triángulo de Queso Fresco Serrano (50g)", "calories": 130, "macros": { "p": 9, "c": 1.5, "g": 10 }, "tags": ["snack", "queso", "proteína", "saludable", "merienda"] },
  { "id": 81, "name": "Maní Tostado sin sal (puñado de 30g)", "calories": 180, "macros": { "p": 8, "c": 6, "g": 14 }, "tags": ["snack", "grasas", "maní", "saludable", "merienda"] }
]
